{
  "source_id": "source-1156",
  "pipeline_version": "distillation-v1",
  "source_hash_sha256": "323973423c5b6b768e5185be9b4b5a0500da26ac90cf46e9339a747df444717d",
  "source_format": "txt",
  "encoding": "gb18030",
  "title_key_hmac_sha256": "18926b9e2a57a6c3bc5bf54a5ba40ea04b55a316fc0fe01720fbfe36b0924c19",
  "title_signal_source": "file_stem",
  "has_author_metadata": false,
  "language": null,
  "rights_status": "user_supplied_for_analysis",
  "redaction_policy": {
    "store_source_title_in_repo": false,
    "store_author_in_repo": false,
    "store_raw_text_in_repo": false
  },
  "dedupe": {
    "strategy": "private-title-key-hmac",
    "duplicate_of": null
  },
  "parse_profile": {
    "chapter_count": 796,
    "volume_count": 1,
    "average_chapter_chars": 3605,
    "boundary_types": [
      "chinese_chapter_heading"
    ],
    "parser_warnings": []
  }
}
