{
  "source_id": "source-0084",
  "pipeline_version": "distillation-v1",
  "source_hash_sha256": "60da07b2b6fac1b10523f62baddecddf18f7649bfeb32bcb7b39615ecccad865",
  "source_format": "txt",
  "encoding": "gb18030",
  "title_key_hmac_sha256": "6bc53997d8071dfff95afae24433b8cb154525821c2b29fbf54b44f8d13f7fbb",
  "title_signal_source": "file_stem",
  "has_author_metadata": false,
  "language": null,
  "rights_status": "user_supplied_for_analysis",
  "redaction_policy": {
    "store_source_title_in_repo": false,
    "store_author_in_repo": false,
    "store_raw_text_in_repo": false
  },
  "dedupe": {
    "strategy": "private-title-key-hmac",
    "duplicate_of": null
  },
  "parse_profile": {
    "chapter_count": 213,
    "volume_count": 1,
    "average_chapter_chars": 2939,
    "boundary_types": [
      "chinese_chapter_heading"
    ],
    "parser_warnings": []
  },
  "genre_hint": "网文"
}
