{
  "source_id": "source-0985",
  "pipeline_version": "distillation-v1",
  "source_hash_sha256": "4aa6038eac8de3c5d42d2f8992e86b5fcfaca65a67411510f4ef21b5ed0ace2c",
  "source_format": "txt",
  "encoding": "gb18030",
  "title_key_hmac_sha256": "8178ac6a1c2cbf7527945771ea79dcb5a9e3b9a7b86cfd0d9c231c37a5d30436",
  "title_signal_source": "file_stem",
  "has_author_metadata": false,
  "language": null,
  "rights_status": "user_supplied_for_analysis",
  "redaction_policy": {
    "store_source_title_in_repo": false,
    "store_author_in_repo": false,
    "store_raw_text_in_repo": false
  },
  "dedupe": {
    "strategy": "private-title-key-hmac",
    "duplicate_of": null
  },
  "parse_profile": {
    "chapter_count": 204,
    "volume_count": 1,
    "average_chapter_chars": 3119,
    "boundary_types": [
      "chinese_chapter_heading"
    ],
    "parser_warnings": []
  }
}
